test/__init__.py
test/test_parser.py
version_updater/__init__.py
version_updater/main.py
version_updater/package_parser.py
version_updater/parser.py
version_updater/requirements_parser.py
version_updater/setup_parser.py
version_updater/yaml_parser.py
version_updater-0.0.4.dist-info/METADATA
version_updater-0.0.4.dist-info/WHEEL
version_updater-0.0.4.dist-info/entry_points.txt
version_updater-0.0.4.dist-info/top_level.txt
version_updater-0.0.4.dist-info/RECORD
