Metadata-Version: 2.1
Name: version-updater
Version: 0.0.4
Summary: Updates semantic versions, either of the artifact itself, or its dependencies
Home-page: UNKNOWN
Author: Jeremy Vickery
Author-email: jeremyvickery@gmail.com
License: MIT
Platform: any
Requires-Dist: semver (==2.13.0)
Requires-Dist: jsonpath-ng (==1.5.2)
Requires-Dist: ruamel.yaml (==0.16.12)
